querido_diario_toolbox/__init__.py
querido_diario_toolbox/__version__.py
querido_diario_toolbox/gazette.py
querido_diario_toolbox/page.py
querido_diario_toolbox/etl/__init__.py
querido_diario_toolbox/etl/apache_tika_text_extractor.py
querido_diario_toolbox/etl/file_transform.py
querido_diario_toolbox/etl/text_extractor.py
querido_diario_toolbox/etl/text_extractor_interface.py
querido_diario_toolbox/process/__init__.py
querido_diario_toolbox/process/edition_process.py
querido_diario_toolbox/process/text_process.py
querido_diario_toolbox/slugs/__init__.py
querido_diario_toolbox/slugs/slugs.py
querido_diario_toolbox-0.3.1.dist-info/LICENSE.md
querido_diario_toolbox-0.3.1.dist-info/METADATA
querido_diario_toolbox-0.3.1.dist-info/WHEEL
querido_diario_toolbox-0.3.1.dist-info/top_level.txt
querido_diario_toolbox-0.3.1.dist-info/RECORD
