Metadata-Version: 2.1
Name: querido-diario-toolbox
Version: 0.3.1
Summary: Este projeto empodera quem deseja processar dados no contexto do Querido Diário e realizar suas próprias análises.
Home-page: https://github.com/okfn-brasil/querido-diario-toolbox
Author: Open Knowledge Brasil
Author-email: queridodiario@ok.org.br
License: MIT
Platform: UNKNOWN
Classifier: License :: OSI Approved :: MIT License
Classifier: Programming Language :: Python
Classifier: Programming Language :: Python :: 3
Classifier: Programming Language :: Python :: 3.8
Classifier: Programming Language :: Python :: Implementation :: CPython
Classifier: Programming Language :: Python :: Implementation :: PyPy
Requires-Python: >=3.8.0
Requires-Dist: python-magic
Requires-Dist: python-slugify
